{
    "LATENCY": {
        "best_latency": 2320,
        "worst_latency": 2320,
        "average_latency": 2320,
        "best_time_latency": "23.200 us",
        "worst_time_latency": "23.200 us",
        "average_time_latency": "23.200 us",
        "min_interval": 2321,
        "max_interval": 2321,
        "Latency": 2320
    },
    "HLS": {
        "LUT": 107503,
        "FF": 64440,
        "DSP": 184,
        "BRAM": 0,
        "URAM": 0,
        "CP": 7.654
    },
    "SYN": {
        "LUT": 83883,
        "FF": 67501,
        "DSP": 184,
        "BRAM": 0,
        "URAM": 0,
        "SRL": 7445,
        "CP": 7.223
    },
    "IMPL": {
        "LUT": 78832,
        "FF": 67444,
        "DSP": 184,
        "BRAM": 0,
        "URAM": 0,
        "SRL": 3787,
        "CP": 9.626,
        "PWR": 1.22
    }
}