{
    "LATENCY": {
        "Latency": 1000
    },
    "HLS": {
        "LUT": 3600,
        "FF": 4482,
        "DSP": 48,
        "BRAM": 0,
        "URAM": 0,
        "CP": 7.734
    },
    "SYN": {
        "LUT": 3356,
        "FF": 3767,
        "DSP": 48,
        "BRAM": 0,
        "URAM": 0,
        "SRL": 0,
        "CP": 7.223
    },
    "IMPL": {
        "LUT": 3291,
        "FF": 3755,
        "DSP": 48,
        "BRAM": 0,
        "URAM": 0,
        "SRL": 0,
        "CP": 8.268,
        "PWR": 0.263
    }
}