{
    "LATENCY": {
        "Latency": 1000
    },
    "HLS": {
        "LUT": 13195,
        "FF": 4233,
        "DSP": 27,
        "BRAM": 0,
        "URAM": 0,
        "CP": 7.734
    },
    "SYN": {
        "LUT": 3959,
        "FF": 3793,
        "DSP": 27,
        "BRAM": 0,
        "URAM": 0,
        "SRL": 0,
        "CP": 7.223
    },
    "IMPL": {
        "LUT": 3899,
        "FF": 3785,
        "DSP": 27,
        "BRAM": 0,
        "URAM": 0,
        "SRL": 0,
        "CP": 8.086,
        "PWR": 0.277
    }
}