{
    "LATENCY": {
        "best_latency": 1168148,
        "worst_latency": 1168159,
        "average_latency": 1168154,
        "best_time_latency": "11.681 ms",
        "worst_time_latency": "11.682 ms",
        "average_time_latency": "11.682 ms",
        "min_interval": 1168149,
        "max_interval": 1168160,
        "Latency": 1168154
    },
    "HLS": {
        "LUT": 9721,
        "FF": 5570,
        "DSP": 6,
        "BRAM": 64,
        "URAM": 0,
        "CP": 7.15
    },
    "SYN": {
        "LUT": 4619,
        "FF": 4341,
        "DSP": 11,
        "BRAM": 64,
        "URAM": 0,
        "SRL": 27,
        "CP": 5.864
    },
    "IMPL": {
        "LUT": 4510,
        "FF": 4335,
        "DSP": 11,
        "BRAM": 64,
        "URAM": 0,
        "SRL": 20,
        "CP": 7.053,
        "PWR": 0.361
    }
}