{
    "LATENCY": {
        "best_latency": 692510,
        "worst_latency": 692510,
        "average_latency": 692510,
        "best_time_latency": "6.925 ms",
        "worst_time_latency": "6.925 ms",
        "average_time_latency": "6.925 ms",
        "min_interval": 692511,
        "max_interval": 692511,
        "Latency": 692510
    },
    "HLS": {
        "LUT": 61013,
        "FF": 48461,
        "DSP": 36,
        "BRAM": 64,
        "URAM": 0,
        "CP": 7.798
    },
    "SYN": {
        "LUT": 44881,
        "FF": 41972,
        "DSP": 53,
        "BRAM": 64,
        "URAM": 0,
        "SRL": 17,
        "CP": 7.223
    },
    "IMPL": {
        "LUT": 44588,
        "FF": 41968,
        "DSP": 53,
        "BRAM": 64,
        "URAM": 0,
        "SRL": 13,
        "CP": 9.794,
        "PWR": 0.556
    }
}