{
    "LATENCY": {
        "best_latency": 7696473,
        "worst_latency": 7696473,
        "average_latency": 7696473,
        "best_time_latency": "76.965 ms",
        "worst_time_latency": "76.965 ms",
        "average_time_latency": "76.965 ms",
        "min_interval": 7696474,
        "max_interval": 7696474,
        "Latency": 7696473
    },
    "HLS": {
        "LUT": 48880,
        "FF": 16738,
        "DSP": 3,
        "BRAM": 64,
        "URAM": 0,
        "CP": 7.15
    },
    "SYN": {
        "LUT": 16142,
        "FF": 16387,
        "DSP": 3,
        "BRAM": 64,
        "URAM": 0,
        "SRL": 8,
        "CP": 5.864
    },
    "IMPL": {
        "LUT": 15986,
        "FF": 16381,
        "DSP": 3,
        "BRAM": 64,
        "URAM": 0,
        "SRL": 5,
        "CP": 9.572,
        "PWR": 0.48
    }
}