{
    "LATENCY": {
        "best_latency": 131368,
        "worst_latency": 131368,
        "average_latency": 131368,
        "best_time_latency": "1.314 ms",
        "worst_time_latency": "1.314 ms",
        "average_time_latency": "1.314 ms",
        "min_interval": 131369,
        "max_interval": 131369,
        "Latency": 131368
    },
    "HLS": {
        "LUT": 12664,
        "FF": 11209,
        "DSP": 6,
        "BRAM": 0,
        "URAM": 0,
        "CP": 7.112
    },
    "SYN": {
        "LUT": 12200,
        "FF": 11155,
        "DSP": 6,
        "BRAM": 0,
        "URAM": 0,
        "SRL": 2702,
        "CP": 5.171
    },
    "IMPL": {
        "LUT": 10564,
        "FF": 11148,
        "DSP": 6,
        "BRAM": 0,
        "URAM": 0,
        "SRL": 1354,
        "CP": 8.262,
        "PWR": 0.379
    }
}