{
    "LATENCY": {
        "Latency": 1000
    },
    "HLS": {
        "LUT": 45517,
        "FF": 8386,
        "DSP": 25,
        "BRAM": 0,
        "URAM": 0,
        "CP": 7.148
    },
    "SYN": {
        "LUT": 13625,
        "FF": 7190,
        "DSP": 25,
        "BRAM": 0,
        "URAM": 0,
        "SRL": 0,
        "CP": 7.223
    },
    "IMPL": {
        "LUT": 13395,
        "FF": 7178,
        "DSP": 25,
        "BRAM": 0,
        "URAM": 0,
        "SRL": 0,
        "CP": 9.678,
        "PWR": 0.496
    }
}