{
    "LATENCY": {
        "best_latency": 756556,
        "worst_latency": 756556,
        "average_latency": 756556,
        "best_time_latency": "7.566 ms",
        "worst_time_latency": "7.566 ms",
        "average_time_latency": "7.566 ms",
        "min_interval": 756557,
        "max_interval": 756557,
        "Latency": 756556
    },
    "HLS": {
        "LUT": 47766,
        "FF": 14517,
        "DSP": 6,
        "BRAM": 64,
        "URAM": 0,
        "CP": 7.15
    },
    "SYN": {
        "LUT": 15221,
        "FF": 14269,
        "DSP": 6,
        "BRAM": 64,
        "URAM": 0,
        "SRL": 12,
        "CP": 5.864
    },
    "IMPL": {
        "LUT": 15067,
        "FF": 14263,
        "DSP": 6,
        "BRAM": 64,
        "URAM": 0,
        "SRL": 10,
        "CP": 9.183,
        "PWR": 0.475
    }
}